langchain/graphs/agensgraph.py
langchain_graph_store_agensgraph-0.1.0.dist-info/LICENSE
langchain_graph_store_agensgraph-0.1.0.dist-info/METADATA
langchain_graph_store_agensgraph-0.1.0.dist-info/WHEEL
langchain_graph_store_agensgraph-0.1.0.dist-info/RECORD
