Metadata-Version: 2.3
Name: langchain-graph-store-agensgraph
Version: 0.1.0
Summary: AgensGraph integration for LangChain graph stores
Keywords: langchain,agensgraph,graph store,integration
Author: Muhammad Taha Naveed
Author-email: skaisw@skaiworldwide.com
Requires-Python: >=3.9,<4.0
Classifier: Programming Language :: Python :: 3
Classifier: Programming Language :: Python :: 3.9
Classifier: Programming Language :: Python :: 3.10
Classifier: Programming Language :: Python :: 3.11
Classifier: Programming Language :: Python :: 3.12
Classifier: Programming Language :: Python :: 3.13
Requires-Dist: langchain (>=0.3.18,<1.0.0)
Requires-Dist: langchain-community (>=0.3.0)
Requires-Dist: langchain-core (>=0.3.34,<1.0.0)
Requires-Dist: psycopg2 (>=2.9.10,<3.0.0)
Project-URL: Homepage, https://github.com/skaiworldwide-oss/agensgraph-ai/tree/main/langchain
Project-URL: Repository, https://github.com/skaiworldwide-oss/agensgraph-ai/tree/main/langchain
